{
  "metadata": {
    "version": "1.0",
    "createdAt": "2026-02-12T02:57:57.016Z",
    "database": "localhost:5432"
  },
  "categories": [
    {
      "id": "4b181d76-37f7-48a0-94ed-4b773ebb9eac",
      "name": "Entradas",
      "slug": "entradas",
      "sortOrder": 1,
      "image": null,
      "active": true,
      "createdAt": "2026-02-12T02:39:30.156Z",
      "updatedAt": "2026-02-12T02:39:30.156Z"
    },
    {
      "id": "c4681339-593a-4f2e-89c4-6d12b0025e4a",
      "name": "Pratos Principais",
      "slug": "pratos-principais",
      "sortOrder": 2,
      "image": null,
      "active": true,
      "createdAt": "2026-02-12T02:39:30.159Z",
      "updatedAt": "2026-02-12T02:39:30.159Z"
    },
    {
      "id": "9951cb1f-ede4-44dc-961e-5dd10ba1ab0f",
      "name": "Sobremesas",
      "slug": "sobremesas",
      "sortOrder": 3,
      "image": null,
      "active": true,
      "createdAt": "2026-02-12T02:39:30.161Z",
      "updatedAt": "2026-02-12T02:39:30.161Z"
    },
    {
      "id": "914ab633-58b9-47f6-8ab6-e39cae47f868",
      "name": "Bebidas",
      "slug": "bebidas",
      "sortOrder": 4,
      "image": null,
      "active": true,
      "createdAt": "2026-02-12T02:39:30.163Z",
      "updatedAt": "2026-02-12T02:39:30.163Z"
    }
  ],
  "dishes": [
    {
      "id": "1db01318-b667-41d3-b812-d63cc2fcd964",
      "name": "<img src=x onerror=\"alert('XSS')\">",
      "slug": "img-src-x-onerror-alert-xss-mliuyjpr",
      "description": "adada",
      "price": 20,
      "image": null,
      "featured": false,
      "active": true,
      "categoryId": "4b181d76-37f7-48a0-94ed-4b773ebb9eac",
      "sortOrder": 0,
      "createdAt": "2026-02-12T02:47:10.673Z",
      "updatedAt": "2026-02-12T02:47:10.673Z",
      "category": {
        "name": "Entradas"
      }
    },
    {
      "id": "7ec689be-1a6d-469d-9dcb-afaf717e8e8d",
      "name": "Bruschetta Italiana",
      "slug": "bruschetta-italiana",
      "description": "Pão italiano tostado com tomates frescos, manjericão, alho e azeite extra virgem.",
      "price": 2890,
      "image": null,
      "featured": true,
      "active": true,
      "categoryId": "4b181d76-37f7-48a0-94ed-4b773ebb9eac",
      "sortOrder": 1,
      "createdAt": "2026-02-12T02:39:30.164Z",
      "updatedAt": "2026-02-12T02:39:30.164Z",
      "category": {
        "name": "Entradas"
      }
    },
    {
      "id": "20684b03-0eba-4997-875b-d00ab52df2dd",
      "name": "Risoto de Funghi",
      "slug": "risoto-funghi",
      "description": "Arroz arbóreo cremoso com mix de cogumelos, parmesão e azeite trufado.",
      "price": 5990,
      "image": null,
      "featured": true,
      "active": true,
      "categoryId": "c4681339-593a-4f2e-89c4-6d12b0025e4a",
      "sortOrder": 1,
      "createdAt": "2026-02-12T02:39:30.172Z",
      "updatedAt": "2026-02-12T02:39:30.172Z",
      "category": {
        "name": "Pratos Principais"
      }
    },
    {
      "id": "855c46d4-4d1d-492b-8552-a58de54828b6",
      "name": "Tiramisù Clássico",
      "slug": "tiramisu-classico",
      "description": "Clássico italiano com biscoito champagne, café espresso e mascarpone.",
      "price": 2490,
      "image": null,
      "featured": false,
      "active": true,
      "categoryId": "9951cb1f-ede4-44dc-961e-5dd10ba1ab0f",
      "sortOrder": 1,
      "createdAt": "2026-02-12T02:39:30.181Z",
      "updatedAt": "2026-02-12T02:39:30.181Z",
      "category": {
        "name": "Sobremesas"
      }
    },
    {
      "id": "187ce438-0bd4-40a3-ab10-cf65f1e9e6b4",
      "name": "Suco Natural",
      "slug": "suco-natural",
      "description": "Suco natural da fruta — laranja, abacaxi, maracujá ou limão.",
      "price": 1290,
      "image": null,
      "featured": false,
      "active": true,
      "categoryId": "914ab633-58b9-47f6-8ab6-e39cae47f868",
      "sortOrder": 1,
      "createdAt": "2026-02-12T02:39:30.183Z",
      "updatedAt": "2026-02-12T02:39:30.183Z",
      "category": {
        "name": "Bebidas"
      }
    },
    {
      "id": "2c396675-41b6-4bb6-ad4e-14f8e4b5cb99",
      "name": "Petit Gâteau",
      "slug": "petit-gateau",
      "description": "Bolo quente de chocolate com coração derretido, acompanhado de sorvete de baunilha.",
      "price": 2890,
      "image": null,
      "featured": false,
      "active": true,
      "categoryId": "9951cb1f-ede4-44dc-961e-5dd10ba1ab0f",
      "sortOrder": 2,
      "createdAt": "2026-02-12T02:39:30.182Z",
      "updatedAt": "2026-02-12T02:39:30.182Z",
      "category": {
        "name": "Sobremesas"
      }
    },
    {
      "id": "b7597ee4-e4cc-433a-a2ca-cfdfbe5633e6",
      "name": "Vinho da Casa (Taça)",
      "slug": "vinho-taca",
      "description": "Seleção do sommelier — tinto ou branco.",
      "price": 1990,
      "image": null,
      "featured": false,
      "active": true,
      "categoryId": "914ab633-58b9-47f6-8ab6-e39cae47f868",
      "sortOrder": 2,
      "createdAt": "2026-02-12T02:39:30.184Z",
      "updatedAt": "2026-02-12T02:39:30.184Z",
      "category": {
        "name": "Bebidas"
      }
    },
    {
      "id": "c13eb79c-60cc-473d-8d3e-8276a082dd47",
      "name": "Carpaccio de Filé Mignon",
      "slug": "carpaccio-file-mignon",
      "description": "Finas fatias de filé mignon com rúcula, parmesão e molho de mostarda e mel.",
      "price": 3990,
      "image": null,
      "featured": false,
      "active": true,
      "categoryId": "4b181d76-37f7-48a0-94ed-4b773ebb9eac",
      "sortOrder": 2,
      "createdAt": "2026-02-12T02:39:30.168Z",
      "updatedAt": "2026-02-12T02:39:30.168Z",
      "category": {
        "name": "Entradas"
      }
    },
    {
      "id": "7a97f361-32ca-4887-84a5-bef76190cc0f",
      "name": "Filé ao Molho Madeira",
      "slug": "file-molho-madeira",
      "description": "Filé mignon grelhado ao ponto, acompanhado de molho madeira e batatas rústicas.",
      "price": 7490,
      "image": null,
      "featured": false,
      "active": true,
      "categoryId": "c4681339-593a-4f2e-89c4-6d12b0025e4a",
      "sortOrder": 2,
      "createdAt": "2026-02-12T02:39:30.175Z",
      "updatedAt": "2026-02-12T02:39:30.175Z",
      "category": {
        "name": "Pratos Principais"
      }
    },
    {
      "id": "ce96889a-461b-4a36-99df-a6fbfa1c7529",
      "name": "Camarões ao Alho",
      "slug": "camaroes-ao-alho",
      "description": "Camarões salteados no azeite com alho, pimenta e ervas frescas.",
      "price": 4590,
      "image": null,
      "featured": true,
      "active": true,
      "categoryId": "4b181d76-37f7-48a0-94ed-4b773ebb9eac",
      "sortOrder": 3,
      "createdAt": "2026-02-12T02:39:30.170Z",
      "updatedAt": "2026-02-12T02:39:30.170Z",
      "category": {
        "name": "Entradas"
      }
    },
    {
      "id": "e9fffb57-ddc6-4a04-b442-cf1502a90096",
      "name": "Salmão Grelhado",
      "slug": "salmao-grelhado",
      "description": "Salmão fresco grelhado com legumes da estação e molho de maracujá.",
      "price": 6990,
      "image": null,
      "featured": false,
      "active": true,
      "categoryId": "c4681339-593a-4f2e-89c4-6d12b0025e4a",
      "sortOrder": 3,
      "createdAt": "2026-02-12T02:39:30.177Z",
      "updatedAt": "2026-02-12T02:39:30.177Z",
      "category": {
        "name": "Pratos Principais"
      }
    },
    {
      "id": "f84eb217-fd49-4544-95e7-fb026a510f02",
      "name": "Massa Pappardelle ao Ragu",
      "slug": "pappardelle-ragu",
      "description": "Massa fresca pappardelle com ragu de carne cozido lentamente por 8 horas.",
      "price": 5490,
      "image": null,
      "featured": false,
      "active": true,
      "categoryId": "c4681339-593a-4f2e-89c4-6d12b0025e4a",
      "sortOrder": 4,
      "createdAt": "2026-02-12T02:39:30.179Z",
      "updatedAt": "2026-02-12T02:39:30.179Z",
      "category": {
        "name": "Pratos Principais"
      }
    }
  ],
  "galleryImages": [],
  "siteConfig": [
    {
      "key": "restaurant_name",
      "value": "Sabor & Arte"
    },
    {
      "key": "restaurant_tagline",
      "value": "Gastronomia que encanta os sentidos"
    },
    {
      "key": "restaurant_description",
      "value": "Há mais de 15 anos trazendo o melhor da culinária contemporânea, unindo ingredientes frescos e técnicas refinadas para criar experiências gastronômicas inesquecíveis."
    },
    {
      "key": "restaurant_address",
      "value": "Rua das Flores, 123 — Centro, São Paulo - SP"
    },
    {
      "key": "restaurant_phone",
      "value": "(11) 99999-8888"
    },
    {
      "key": "restaurant_email",
      "value": "contato@saborarte.com.br"
    },
    {
      "key": "whatsapp_number",
      "value": "5511999998888"
    },
    {
      "key": "whatsapp_message",
      "value": "Olá! Vi o site do Sabor & Arte e gostaria de fazer uma reserva."
    },
    {
      "key": "hero_title",
      "value": "Uma experiência gastronômica única"
    },
    {
      "key": "hero_subtitle",
      "value": "Ingredientes frescos, técnicas refinadas e sabores que contam histórias."
    },
    {
      "key": "about_title",
      "value": "Nossa História"
    },
    {
      "key": "about_text",
      "value": "Fundado em 2010, o Sabor & Arte nasceu da paixão por unir ingredientes da mais alta qualidade com técnicas culinárias contemporâneas. Nosso chef executivo, com passagens por restaurantes estrelados na Europa, traz para cada prato uma combinação única de tradição e inovação."
    },
    {
      "key": "opening_hours",
      "value": "Seg-Qui: 11h30–15h / 18h30–23h | Sex-Sáb: 11h30–00h | Dom: 11h30–16h"
    },
    {
      "key": "google_maps_embed",
      "value": "https://www.google.com/maps/embed?pb=!1m18!1m12!1m3!1d3657.1976670254753!2d-46.65529378502211!3d-23.56517098468082!2m3!1f0!2f0!3f0!3m2!1i1024!2i768!4f13.1!3m3!1m2!1s0x0%3A0x0!2zMjPCsDMzJzU0LjYiUyA0NsKwMzknMTEuMSJX!5e0!3m2!1spt-BR!2sbr!4v1234567890"
    },
    {
      "key": "instagram_url",
      "value": "https://instagram.com/saborarte"
    },
    {
      "key": "facebook_url",
      "value": "https://facebook.com/saborarte"
    },
    {
      "key": "footer_text",
      "value": "© 2026 Sabor & Arte. Todos os direitos reservados."
    }
  ],
  "adminUsers": [
    {
      "id": "2ec37559-85e8-4d13-a021-522c1f735650",
      "email": "admin@restaurante.com",
      "name": "Administrador",
      "role": "ADMIN",
      "createdAt": "2026-02-12T02:39:30.150Z"
    }
  ]
}